danger_py_jscpd/__init__.py
danger_py_jscpd/plugin.py
danger_py_jscpd/report_parser.py
danger_py_jscpd-0.1.0.dist-info/LICENSE
danger_py_jscpd-0.1.0.dist-info/WHEEL
danger_py_jscpd-0.1.0.dist-info/METADATA
danger_py_jscpd-0.1.0.dist-info/RECORD
