Metadata-Version: 2.1
Name: danger-py-jscpd
Version: 0.1.0
Summary: danger-python plugin for detecting copy/paste
License: MIT
Author: Mateusz Szklarek
Author-email: mateusz.szklarek@gmail.com
Requires-Python: >=3.7,<4.0
Classifier: License :: OSI Approved :: MIT License
Classifier: Programming Language :: Python :: 3
Classifier: Programming Language :: Python :: 3.7
Classifier: Programming Language :: Python :: 3.8
